aerospike_flask/cache/__init__.py
aerospike_flask/cache/aerospike.py
aerospike_flask_cache-0.1.1.dist-info/METADATA
aerospike_flask_cache-0.1.1.dist-info/WHEEL
aerospike_flask_cache-0.1.1.dist-info/licenses/LICENSE
aerospike_flask_cache-0.1.1.dist-info/RECORD
