Metadata-Version: 2.3
Name: aerospike-flask-cache
Version: 0.1.1
Summary: Aerospike cache backend for Flask
Author-email: Micah Carrick <micahcarrick@gmail.com>
License-File: LICENSE
Requires-Python: <=3.13,>=3.8
Requires-Dist: aerospike
Requires-Dist: flask-caching
